jrpymc3/__init__.py
jrpymc3/__version__.py
jrpymc3-0.1.1.dist-info/WHEEL
jrpymc3-0.1.1.dist-info/METADATA
jrpymc3-0.1.1.dist-info/RECORD
