Metadata-Version: 2.1
Name: jrpymc3
Version: 0.1.1
Summary: Jumping Rivers: Bayesian Inference with PyMC3
Author: Jamie
Author-email: jamie@jumpingrivers.com
Requires-Python: >=3.6,<4.0
Classifier: Programming Language :: Python :: 3
Classifier: Programming Language :: Python :: 3.6
Classifier: Programming Language :: Python :: 3.7
Classifier: Programming Language :: Python :: 3.8
Classifier: Programming Language :: Python :: 3.9
